jamfmcp/__about__.py
jamfmcp/__init__.py
jamfmcp/api.py
jamfmcp/auth.py
jamfmcp/cli.py
jamfmcp/health_analyzer.py
jamfmcp/server.py
jamfmcp/sofa.py
jamfmcp/jamfsdk/__about__.py
jamfmcp/jamfsdk/__init__.py
jamfmcp/jamfsdk/exceptions.py
jamfmcp/jamfsdk/helpers.py
jamfmcp/jamfsdk/clients/__init__.py
jamfmcp/jamfsdk/clients/auth.py
jamfmcp/jamfsdk/clients/classic_api.py
jamfmcp/jamfsdk/clients/jcds2.py
jamfmcp/jamfsdk/clients/webhooks.py
jamfmcp/jamfsdk/clients/pro_api/__init__.py
jamfmcp/jamfsdk/clients/pro_api/pagination.py
jamfmcp/jamfsdk/models/__init__.py
jamfmcp/jamfsdk/models/client.py
jamfmcp/jamfsdk/models/classic/__init__.py
jamfmcp/jamfsdk/models/classic/advanced_computer_searches.py
jamfmcp/jamfsdk/models/classic/categories.py
jamfmcp/jamfsdk/models/classic/computer_groups.py
jamfmcp/jamfsdk/models/classic/computers.py
jamfmcp/jamfsdk/models/classic/criteria.py
jamfmcp/jamfsdk/models/classic/network_segments.py
jamfmcp/jamfsdk/models/classic/packages.py
jamfmcp/jamfsdk/models/pro/__init__.py
jamfmcp/jamfsdk/models/pro/api_options.py
jamfmcp/jamfsdk/models/pro/computers.py
jamfmcp/jamfsdk/models/pro/jcds2.py
jamfmcp/jamfsdk/models/pro/mdm.py
jamfmcp/jamfsdk/models/pro/mobile_devices.py
jamfmcp/jamfsdk/models/pro/packages.py
jamfmcp/jamfsdk/models/webhooks/__init__.py
jamfmcp/jamfsdk/models/webhooks/webhooks.py
jamfmcp-1.0.2.dist-info/licenses/LICENSE
jamfmcp-1.0.2.dist-info/METADATA
jamfmcp-1.0.2.dist-info/WHEEL
jamfmcp-1.0.2.dist-info/entry_points.txt
jamfmcp-1.0.2.dist-info/top_level.txt
jamfmcp-1.0.2.dist-info/RECORD
