Metadata-Version: 2.4
Name: jamfmcp
Version: 1.0.2
Summary: An async MCP server for Jamf Pro integration providing computer health analysis
Author-email: Andrew Lerman <info@liquidzoo.io>
License: 
Project-URL: Homepage, https://jamfmcp.readthedocs.io/en/latest
Project-URL: Documentation, https://jamfmcp.readthedocs.io/en/latest
Project-URL: Repository, https://github.com/liquidz00/jamfmcp
Project-URL: Issues, https://github.com/liquidz00/jamfmcp/issues/new
Keywords: jamf,pro,jss,mcp,mdm,fastmcp
Requires-Python: >=3.13
License-File: LICENSE
Requires-Dist: asyncclick>=8.3.0.7
Requires-Dist: defusedxml
Requires-Dist: dicttoxml<2,>=1.7.16
Requires-Dist: faker>=37.12.0
Requires-Dist: fastmcp>=2.11.3
Requires-Dist: httpx>=0.27.0
Requires-Dist: keyring>=25.6.0
Requires-Dist: polyfactory>=2.22.3
Requires-Dist: pydantic<3,>=2
Provides-Extra: dev
Requires-Dist: autodoc-pydantic; extra == "dev"
Requires-Dist: build; extra == "dev"
Requires-Dist: deepdiff; extra == "dev"
Requires-Dist: myst-parser; extra == "dev"
Requires-Dist: pre-commit>=4.3.0; extra == "dev"
Requires-Dist: pytest>=8.2.2; extra == "dev"
Requires-Dist: pytest-asyncio>=0.23.5; extra == "dev"
Requires-Dist: pytest-cov>=4.0.0; extra == "dev"
Requires-Dist: pytest-mock>=3.14.0; extra == "dev"
Requires-Dist: ruff>=0.5.1; extra == "dev"
Requires-Dist: sphinx>=7.3.7; extra == "dev"
Requires-Dist: sphinx-design; extra == "dev"
Requires-Dist: sphinx-copybutton; extra == "dev"
Requires-Dist: sphinx-togglebutton; extra == "dev"
Requires-Dist: shibuya>=2025.11.10; extra == "dev"
Requires-Dist: sphinx-iconify>=0.2.1; extra == "dev"
Dynamic: license-file
